stockpick/.DS_Store
stockpick/__init__.py
stockpick/corpus_process.py
stockpick/enum_table
stockpick/extractor.py
stockpick/extractor_new.py
stockpick/f10.txt
stockpick/gupiao_dict.txt
stockpick/index_table
stockpick/index_table.csv
stockpick/match_words.csv
stockpick/match_words_copy.csv
stockpick/question.txt
stockpick/scope_table
stockpick/sentences.txt
stockpick/stock.json
stockpick/unit_table
stockpick/utils.py
stockpick-1.4.2.dist-info/METADATA
stockpick-1.4.2.dist-info/WHEEL
stockpick-1.4.2.dist-info/top_level.txt
stockpick-1.4.2.dist-info/RECORD
