Metadata-Version: 2.1
Name: stockpick
Version: 1.4.2
Summary: version
Home-page: https://pypi.org/project/stockpick
Author: huyi
Author-email: huyi@datagrand.com
Requires-Python: >=3.6.0
Requires-Dist: jieba (==0.42.1)
